dsym/__init__.py
dsym/dsym.py
dsym-1.0.3.dist-info/licenses/LICENSE
dsym-1.0.3.dist-info/METADATA
dsym-1.0.3.dist-info/WHEEL
dsym-1.0.3.dist-info/entry_points.txt
dsym-1.0.3.dist-info/top_level.txt
dsym-1.0.3.dist-info/RECORD
