Metadata-Version: 2.4
Name: dsym
Version: 1.0.3
Summary: DSYM: manage your dotfiles with git
Author-email: 0x17 <post@nerdbude.com>
License-Expression: AGPL-3.0-or-later
Requires-Python: >=3.7
License-File: LICENSE
Dynamic: license-file
